{
	"physics":[
		{
			"name": "Mechanics", 
			"sections":[
				{
					"name": "Kinematics",
					"complexity": "average",
					"interest": "great",
					"bool": true


					
				},
				{
					"name": "Hydrodynamics",
					"complexity": "4",
					"interest": "3",
					"bool": false

				}
			]
		},
			{
			 	"note": "addition",
			 	"useful links": 
			 	[
			 		{ 	[url=https://gitlocalize-staging.herokuapp.com/repo/1902/fr?utm_source=badge][img]https://gitlocalize-staging.herokuapp.com/repo/1902/fr /badge.svg[/img][/url] 
			 }
			 	]
			
		
	},
			{
			 	"name": "Electricity",
			 	"sections":[
			 		{
			 	    "name": "electrostatics",
					"complexity": "four ",
					"interest": "five"
			 }
			 	]
			}
		
	]
}
